scparadise/__init__.py
scparadise/scadam.py
scparadise/sceve.py
scparadise/scnoah.py
scparadise-0.6.0b0.dist-info/METADATA
scparadise-0.6.0b0.dist-info/WHEEL
scparadise-0.6.0b0.dist-info/licenses/LICENSE.txt
scparadise-0.6.0b0.dist-info/RECORD
