Metadata-Version: 2.4
Name: scparadise
Version: 0.6.0b0
Summary: Single-Cell Analysis Annotation and Modality Prediction.
Project-URL: Source, https://github.com/Chechekhins/scParadise
Author: Vadim Chechekhin, Elizaveta Chechekhina
Maintainer-email: Vadim Chechekhin <vadimchex97@gmail.com>, Elizaveta Chechekhina <voynovaes.pharm@gmail.com>
License: MIT License
License-File: LICENSE.txt
Classifier: Development Status :: 4 - Beta
Classifier: Environment :: GPU
Classifier: Framework :: Jupyter
Classifier: Intended Audience :: Developers
Classifier: Intended Audience :: Science/Research
Classifier: License :: OSI Approved :: MIT License
Classifier: Natural Language :: English
Classifier: Operating System :: Microsoft :: Windows
Classifier: Operating System :: POSIX :: Linux
Classifier: Programming Language :: Python :: 3
Classifier: Programming Language :: Python :: 3.7
Classifier: Programming Language :: Python :: 3.8
Classifier: Programming Language :: Python :: 3.9
Classifier: Programming Language :: Python :: 3.10
Classifier: Topic :: Scientific/Engineering :: Artificial Intelligence
Classifier: Topic :: Scientific/Engineering :: Bio-Informatics
Requires-Python: >=3.7
Requires-Dist: anndata>=0.8
Requires-Dist: imbalanced-learn>=0.9.0
Requires-Dist: muon>=0.1.0
Requires-Dist: numba>=0.56
Requires-Dist: numpy>=1.17
Requires-Dist: optuna>=3.0.0
Requires-Dist: packaging>=21.3
Requires-Dist: pytorch-tabnet>=4.0
Requires-Dist: scanpy>=1.1
Requires-Dist: scikit-learn>=0.21
Requires-Dist: scipy>=1.4
Requires-Dist: shap>=0.46.0
Requires-Dist: torch>=1.3
Requires-Dist: tqdm>=4.36
